{
  "categories": [
    "Artifact/Package Management",
    "Collaboration",
    "Configuration Automation",
    "Container Orchestration",
    "Database Management",
    "Deployment",
    "Enterprise Agile Planning",
    "IT Service Management",
    "PaaS/Container Service",
    "Release Management",
    "Security",
    "Source Control Management",
    "Testing",
    "Value Stream Management",
    "Continuous Integration",
    "Public Cloud",
    "Developer Portal",
    "DevOps AI-ML Analytics"
  ],
  "tools": [
    { "n": 1, "s": "Aja", "name": "Atlassian Jira Align", "cat": "Enterprise Agile Planning", "r": 1, "c": 1 },
    { "n": 2, "s": "GitGi", "name": "GitGi", "cat": "Source Control Management", "r": 1, "c": 2 },
    { "n": 3, "s": "Daa", "name": "Digital.ai Agility", "cat": "Enterprise Agile Planning", "r": 1, "c": 3 },
    { "n": 4, "s": "Tp", "name": "Targetprocess", "cat": "Enterprise Agile Planning", "r": 1, "c": 4 },
    { "n": 5, "s": "Azp", "name": "Azure DevOps Pipelines", "cat": "Continuous Integration", "r": 1, "c": 5 },
    { "n": 6, "s": "Ow", "name": "OWASP ZAP", "cat": "Security", "r": 1, "c": 6 },
    { "n": 7, "s": "Dap", "name": "Digital.ai App Protection", "cat": "Security", "r": 1, "c": 7 },
    { "n": 8, "s": "Ck", "name": "CyberArk Conjur", "cat": "Security", "r": 1, "c": 8 },
    { "n": 9, "s": "Sw", "name": "ServiceNow", "cat": "IT Service Management", "r": 1, "c": 9 },
    { "n": 10, "s": "Gh", "name": "GitHub", "cat": "Source Control Management", "r": 1, "c": 10 },
    { "n": 11, "s": "Pv", "name": "Planview", "cat": "Value Stream Management", "r": 1, "c": 11 },
    { "n": 12, "s": "Br", "name": "Broadcom Rally", "cat": "Enterprise Agile Planning", "r": 1, "c": 12 },
    { "n": 13, "s": "Dad", "name": "Digital.ai Deploy", "cat": "Deployment", "r": 1, "c": 13 },
    { "n": 14, "s": "Sni", "name": "Sonatype Nexus IQ", "cat": "Artifact/Package Management", "r": 1, "c": 14 },
    { "n": 15, "s": "Aq", "name": "Aqua Security", "cat": "Security", "r": 1, "c": 15 },
    { "n": 16, "s": "Vc", "name": "Veracode", "cat": "Security", "r": 1, "c": 16 },
    { "n": 17, "s": "Bi", "name": "BMC Helix ITSM", "cat": "IT Service Management", "r": 1, "c": 17 },
    { "n": 18, "s": "Gls", "name": "GitLab SCM", "cat": "Source Control Management", "r": 1, "c": 18 },

    { "n": 19, "s": "Aj", "name": "Atlassian Jira", "cat": "Enterprise Agile Planning", "r": 2, "c": 1 },
    { "n": 20, "s": "Dd", "name": "Datadog", "cat": "Value Stream Management", "r": 2, "c": 2 },
    { "n": 21, "s": "Bp", "name": "Big Panda", "cat": "Value Stream Management", "r": 2, "c": 3 },
    { "n": 22, "s": "In", "name": "Instana", "cat": "Value Stream Management", "r": 2, "c": 4 },
    { "n": 23, "s": "Acp", "name": "AWS CodePipeline", "cat": "Continuous Integration", "r": 2, "c": 5 },
    { "n": 24, "s": "Mt", "name": "Microsoft Teams", "cat": "Collaboration", "r": 2, "c": 6 },
    { "n": 25, "s": "Rha", "name": "Red Hat Ansible", "cat": "Configuration Automation", "r": 2, "c": 7 },
    { "n": 26, "s": "Ht", "name": "HashiCorp Terraform", "cat": "Configuration Automation", "r": 2, "c": 8 },
    { "n": 27, "s": "Dk", "name": "Docker", "cat": "Container Orchestration", "r": 2, "c": 9 },
    { "n": 28, "s": "Rho", "name": "Red Hat OpenShift", "cat": "Container Orchestration", "r": 2, "c": 10 },
    { "n": 29, "s": "Lb", "name": "Liquibase", "cat": "Database Management", "r": 2, "c": 11 },
    { "n": 30, "s": "Dp", "name": "Delphix", "cat": "Database Management", "r": 2, "c": 12 },
    { "n": 31, "s": "Ud", "name": "UrbanCode Deploy", "cat": "Deployment", "r": 2, "c": 13 },
    { "n": 32, "s": "Om", "name": "OpxMx", "cat": "Developer Portal", "r": 2, "c": 14 },
    { "n": 33, "s": "Hv", "name": "HashiCorp Vault", "cat": "Security", "r": 2, "c": 15 },
    { "n": 34, "s": "Sy", "name": "Snyk", "cat": "Security", "r": 2, "c": 16 },
    { "n": 35, "s": "Pd", "name": "PagerDuty", "cat": "IT Service Management", "r": 2, "c": 17 },
    { "n": 36, "s": "Abb", "name": "Atlassian Bitbucket", "cat": "Source Control Management", "r": 2, "c": 18 },

    { "n": 37, "s": "Sp", "name": "Splunk", "cat": "Value Stream Management", "r": 3, "c": 1 },
    { "n": 38, "s": "Ad", "name": "AppDynamics", "cat": "Value Stream Management", "r": 3, "c": 2 },
    { "n": 39, "s": "Kb", "name": "Kibana", "cat": "Value Stream Management", "r": 3, "c": 3 },
    { "n": 40, "s": "Dar", "name": "Digital.ai Release", "cat": "Release Management", "r": 3, "c": 4 },
    { "n": 41, "s": "Ur", "name": "UrbanCode Release", "cat": "Release Management", "r": 3, "c": 5 },
    { "n": 42, "s": "Ac", "name": "Atlassian Confluence", "cat": "Collaboration", "r": 3, "c": 6 },
    { "n": 43, "s": "Ch", "name": "Chef", "cat": "Configuration Automation", "r": 3, "c": 7 },
    { "n": 44, "s": "Acf", "name": "AWS CloudFormation", "cat": "Configuration Automation", "r": 3, "c": 8 },
    { "n": 45, "s": "Ku", "name": "Kubernetes", "cat": "Container Orchestration", "r": 3, "c": 9 },
    { "n": 46, "s": "Ak", "name": "Amazon EKS", "cat": "Container Orchestration", "r": 3, "c": 10 },
    { "n": 47, "s": "De", "name": "Docker Enterprise", "cat": "Container Orchestration", "r": 3, "c": 11 },
    { "n": 48, "s": "Rf", "name": "Redgate Flyway", "cat": "Database Management", "r": 3, "c": 12 },
    { "n": 49, "s": "Ha", "name": "Harness", "cat": "Deployment", "r": 3, "c": 13 },
    { "n": 50, "s": "Pi", "name": "Pulumi", "cat": "Configuration Automation", "r": 3, "c": 14 },
    { "n": 51, "s": "Sr", "name": "SonarQube", "cat": "Testing", "r": 3, "c": 15 },
    { "n": 52, "s": "Ff", "name": "Micro Focus Fortify SCA", "cat": "Security", "r": 3, "c": 16 },
    { "n": 53, "s": "Azf", "name": "Azure Functions", "cat": "Public Cloud", "r": 3, "c": 17 },
    { "n": 54, "s": "Ci", "name": "Compuware ISPW", "cat": "Release Management", "r": 3, "c": 18 },

    { "n": 55, "s": "Dt", "name": "Dynatrace", "cat": "Value Stream Management", "r": 4, "c": 1 },
    { "n": 56, "s": "Nr", "name": "New Relic", "cat": "Value Stream Management", "r": 4, "c": 2 },
    { "n": 57, "s": "Dh", "name": "Docker Hub", "cat": "Artifact/Package Management", "r": 4, "c": 3 },
    { "n": 58, "s": "Np", "name": "npm", "cat": "Artifact/Package Management", "r": 4, "c": 4 },
    { "n": 59, "s": "Ja", "name": "JFrog Artifactory", "cat": "Artifact/Package Management", "r": 4, "c": 5 },
    { "n": 60, "s": "So", "name": "Stack Overflow", "cat": "Collaboration", "r": 4, "c": 6 },
    { "n": 61, "s": "Sl", "name": "Slack", "cat": "Collaboration", "r": 4, "c": 7 },
    { "n": 62, "s": "Hc", "name": "HachiCorp Consul", "cat": "Configuration Automation", "r": 4, "c": 8 },
    { "n": 63, "s": "Pu", "name": "Puppet", "cat": "Configuration Automation", "r": 4, "c": 9 },
    { "n": 64, "s": "Azk", "name": "Azure AKS", "cat": "Container Orchestration", "r": 4, "c": 10 },
    { "n": 65, "s": "Ae", "name": "Amazon ECS", "cat": "Container Orchestration", "r": 4, "c": 11 },
    { "n": 66, "s": "Qt", "name": "Quest Road", "cat": "Developer Portal", "r": 4, "c": 12 },
    { "n": 67, "s": "Sk", "name": "Spinnaker", "cat": "Release Management", "r": 4, "c": 13 },
    { "n": 68, "s": "Od", "name": "Octopus Deploy", "cat": "Release Management", "r": 4, "c": 14 },
    { "n": 69, "s": "Sb", "name": "Synapsys Black Duck", "cat": "Security", "r": 4, "c": 15 },
    { "n": 70, "s": "Cx", "name": "Checkmarx SAST", "cat": "Security", "r": 4, "c": 16 },
    { "n": 71, "s": "He", "name": "Heroku", "cat": "PaaS/Container Service", "r": 4, "c": 17 },
    { "n": 72, "s": "Al", "name": "AWS Lambda", "cat": "Public Cloud", "r": 4, "c": 18 },

    { "n": 73, "s": "Gr", "name": "Grafana", "cat": "Value Stream Management", "r": 5, "c": 1 },
    { "n": 74, "s": "El", "name": "Elastic ELK Stack", "cat": "Value Stream Management", "r": 5, "c": 2 },
    { "n": 75, "s": "Yn", "name": "Yarn", "cat": "Artifact/Package Management", "r": 5, "c": 3 },
    { "n": 76, "s": "Nu", "name": "NuGet", "cat": "Artifact/Package Management", "r": 5, "c": 4 },
    { "n": 77, "s": "Snx", "name": "Sonatype Nexus", "cat": "Artifact/Package Management", "r": 5, "c": 5 },
    { "n": 78, "s": "Mm", "name": "Mattermost", "cat": "Collaboration", "r": 5, "c": 6 },
    { "n": 79, "s": "Mr", "name": "Miro", "cat": "Collaboration", "r": 5, "c": 7 },
    { "n": 80, "s": "Ml", "name": "Mural", "cat": "Collaboration", "r": 5, "c": 8 },
    { "n": 81, "s": "Hp", "name": "HashiCorp Packer", "cat": "Configuration Automation", "r": 5, "c": 9 },
    { "n": 82, "s": "Gk", "name": "Google GKE", "cat": "Container Orchestration", "r": 5, "c": 10 },
    { "n": 83, "s": "Hm", "name": "Helm", "cat": "Container Orchestration", "r": 5, "c": 11 },
    { "n": 84, "s": "Fx", "name": "Flux", "cat": "Deployment", "r": 5, "c": 12 },
    { "n": 85, "s": "Tk", "name": "Tekton", "cat": "Continuous Integration", "r": 5, "c": 13 },
    { "n": 86, "s": "Acd", "name": "AWS CodeDeploy", "cat": "Deployment", "r": 5, "c": 14 },
    { "n": 87, "s": "Sn", "name": "Snort", "cat": "Security", "r": 5, "c": 15 },
    { "n": 88, "s": "Pbs", "name": "PortSwigger Burp Suite", "cat": "Security", "r": 5, "c": 16 },
    { "n": 89, "s": "Gf", "name": "Google Firebase", "cat": "Public Cloud", "r": 5, "c": 17 },
    { "n": 90, "s": "Cf", "name": "Cloud Foundry", "cat": "PaaS/Container Service", "r": 5, "c": 18 },

    { "n": 91, "s": "Jn", "name": "Jenkins", "cat": "Continuous Integration", "r": 6, "c": 1 },
    { "n": 92, "s": "Azc", "name": "Azure DevOps Code", "cat": "Continuous Integration", "r": 6, "c": 2 },
    { "n": 93, "s": "Glc", "name": "GitLab CI", "cat": "Continuous Integration", "r": 6, "c": 3 },
    { "n": 94, "s": "Tr", "name": "Travis CI", "cat": "Continuous Integration", "r": 6, "c": 4 },
    { "n": 95, "s": "Cc", "name": "Circle CI", "cat": "Continuous Integration", "r": 6, "c": 5 },
    { "n": 96, "s": "Mv", "name": "Maven", "cat": "Artifact/Package Management", "r": 6, "c": 6 },
    { "n": 97, "s": "Ab", "name": "Atlassian Bamboo", "cat": "Release Management", "r": 6, "c": 7 },
    { "n": 98, "s": "Ga", "name": "Github Actions", "cat": "Continuous Integration", "r": 6, "c": 8 },
    { "n": 99, "s": "Acb", "name": "AWS CodeBuild", "cat": "Continuous Integration", "r": 6, "c": 9 },
    { "n": 100, "s": "Cf", "name": "CodeFresh", "cat": "Continuous Integration", "r": 6, "c": 10 },
    { "n": 101, "s": "Az", "name": "Azure", "cat": "Public Cloud", "r": 6, "c": 11 },
    { "n": 102, "s": "Gc", "name": "Google Cloud", "cat": "Public Cloud", "r": 6, "c": 12 },
    { "n": 103, "s": "Aws", "name": "AWS", "cat": "Public Cloud", "r": 6, "c": 13 },
    { "n": 104, "s": "Os", "name": "OpenStack", "cat": "Public Cloud", "r": 6, "c": 14 },
    { "n": 105, "s": "Bg", "name": "Backstage", "cat": "Developer Portal", "r": 6, "c": 15 },
    { "n": 106, "s": "Tt", "name": "Tricentis Tosca", "cat": "Testing", "r": 6, "c": 16 },
    { "n": 107, "s": "Se", "name": "Selenium", "cat": "Testing", "r": 6, "c": 17 },
    { "n": 108, "s": "Ju", "name": "JUnit", "cat": "Testing", "r": 6, "c": 18 },

    { "n": 109, "s": "Sl", "name": "Sauce Labs", "cat": "Testing", "r": 7, "c": 1 },
    { "n": 110, "s": "Ct", "name": "Compuware Topaz", "cat": "Developer Portal", "r": 7, "c": 2 },
    { "n": 111, "s": "Ap", "name": "Appium", "cat": "Testing", "r": 7, "c": 3 },
    { "n": 112, "s": "Sq", "name": "Squash TM", "cat": "Testing", "r": 7, "c": 4 },
    { "n": 113, "s": "Cu", "name": "Cucumber", "cat": "Testing", "r": 7, "c": 5 },
    { "n": 114, "s": "Jm", "name": "Jmeter", "cat": "Testing", "r": 7, "c": 6 },
    { "n": 115, "s": "Pa", "name": "Parasoft", "cat": "Testing", "r": 7, "c": 7 },
    { "n": 116, "s": "Dac", "name": "Digital.ai Continuous Testing", "cat": "Testing", "r": 7, "c": 8 },
    { "n": 117, "s": "Da", "name": "Digital.ai", "cat": "DevOps AI-ML Analytics", "r": 7, "c": 9 },
    { "n": 118, "s": "Pvz", "name": "Planview Viz", "cat": "Value Stream Management", "r": 7, "c": 10 },
    { "n": 119, "s": "Pr", "name": "Plutora", "cat": "Release Management", "r": 7, "c": 11 },
    { "n": 120, "s": "Dai", "name": "Digital.ai Intelligence", "cat": "DevOps AI-ML Analytics", "r": 7, "c": 12 }
  ]
}
